[
  {
    "title": "Chromecast 2015 dfabeba",
    "img": "",
    "prices": {
      "btc": {
        "id": "btc",
        "actualPrice": 0.00000995,
        "undiscountedPrice": 0.000000052,
        "discount": 12
      },
      "stq": {
        "id": "stq",
        "actualPrice": 345475467,
        "undiscountedPrice": 345475467,
        "discount": 12
      },
      "eur": {
        "id": "eur",
        "actualPrice": 2537,
        "undiscountedPrice": 3860,
        "discount": 12
      }
    },
    "qualityAssurance": false
  },
  {
    "title": "Планшет Apple iPad 32Gb Wi-Fi Apple iPad 32Gb Wi-Fi",
    "img": "",
    "prices": {
      "btc": {
        "id": "btc",
        "actualPrice": 0.00000995,
        "undiscountedPrice": 0.000000052,
        "discount": 12
      },
      "stq": {
        "id": "stq",
        "actualPrice": 345475467,
        "undiscountedPrice": 345475467,
        "discount": 12
      },
      "eur": {
        "id": "eur",
        "actualPrice": 2537,
        "undiscountedPrice": 3860,
        "discount": 12
      }
    },
    "qualityAssurance": false
  },
  {
    "title": "Chromecast 2015 dfabeba Handcrafted toys msde of cotton",
    "img": "",
    "prices": {
      "btc": {
        "id": "btc",
        "actualPrice": 0.00000995,
        "undiscountedPrice": 0.000000052,
        "discount": 12
      },
      "stq": {
        "id": "stq",
        "actualPrice": 345475467,
        "undiscountedPrice": 345475467,
        "discount": 12
      },
      "eur": {
        "id": "eur",
        "actualPrice": 2537,
        "undiscountedPrice": 3860,
        "discount": 12
      }
    },
    "qualityAssurance": false
  },
  {
    "title": "Планшет Apple iPad 32Gb Wi-Fi Apple iPad 32Gb Wi-Fi",
    "img": "",
    "prices": {
      "btc": {
        "id": "btc",
        "actualPrice": 0.00000995,
        "undiscountedPrice": 0.000000052,
        "discount": 12
      },
      "stq": {
        "id": "stq",
        "actualPrice": 345475467,
        "undiscountedPrice": 345475467,
        "discount": 12
      },
      "eur": {
        "id": "eur",
        "actualPrice": 2537,
        "undiscountedPrice": 3860,
        "discount": 12
      }
    },
    "qualityAssurance": false
  },
  {
    "title": "Chromecast 2015 dfabeba",
    "img": "",
    "prices": {
      "btc": {
        "id": "btc",
        "actualPrice": 0.00000995,
        "undiscountedPrice": 0.000000052,
        "discount": 12
      },
      "stq": {
        "id": "stq",
        "actualPrice": 345475467,
        "undiscountedPrice": 345475467,
        "discount": 12
      },
      "eur": {
        "id": "eur",
        "actualPrice": 2537,
        "undiscountedPrice": 3860,
        "discount": 12
      }
    },
    "qualityAssurance": false
  },
  {
    "title": "Chromecast 2015 dfabeba",
    "img": "",
    "prices": {
      "btc": {
        "id": "btc",
        "actualPrice": 0.00000995,
        "undiscountedPrice": 0.000000052,
        "discount": 12
      },
      "stq": {
        "id": "stq",
        "actualPrice": 345475467,
        "undiscountedPrice": 345475467,
        "discount": 12
      },
      "eur": {
        "id": "eur",
        "actualPrice": 2537,
        "undiscountedPrice": 3860,
        "discount": 12
      }
    },
    "qualityAssurance": false
  }
]